django_app_bootstrap/__init__.py
django_app_bootstrap/app.py
django_app_bootstrap/bootstrap_files/__init__.py
django_app_bootstrap/bootstrap_files/admin.html
django_app_bootstrap/bootstrap_files/api.html
django_app_bootstrap/bootstrap_files/forms.html
django_app_bootstrap/bootstrap_files/serializers.html
django_app_bootstrap/bootstrap_files/urls.html
django_app_bootstrap/bootstrap_files/views.html
django_app_bootstrap/bootstrap_files/selectors/selector.html
django_app_bootstrap/bootstrap_files/selectors/selector.py
django_app_bootstrap/bootstrap_files/services/service.html
django_app_bootstrap/bootstrap_files/templates/list.html
django_app_bootstrap/management/__init__.py
django_app_bootstrap/management/commands/__init__.py
django_app_bootstrap/management/commands/bootstrap_app.py
django_app_bootstrap-1.0.8.dist-info/LICENSE
django_app_bootstrap-1.0.8.dist-info/METADATA
django_app_bootstrap-1.0.8.dist-info/WHEEL
django_app_bootstrap-1.0.8.dist-info/top_level.txt
django_app_bootstrap-1.0.8.dist-info/RECORD
