Metadata-Version: 2.1
Name: django-app-bootstrap
Version: 1.0.8
Summary: Quickly generate application from django model files
Home-page: https://github.com/opencbsoft/django-app-bootstrap
Author: Cristian Boboc
Author-email: cristi@cbsoft.ro
License: GNU
Platform: UNKNOWN
